lauexplore/__init__.py
lauexplore/_defaults/__init__.py
lauexplore/_defaults/naming.py
lauexplore/_defaults/rounding.py
lauexplore/_parsers/__init__.py
lauexplore/_parsers/_fitfile.py
lauexplore/_parsers/_h5.py
lauexplore/_parsers/_peaklist.py
lauexplore/_parsers/_yamlfile.py
lauexplore/_utils/__init__.py
lauexplore/_utils/_cbar.py
lauexplore/_utils/_compute_zlimits.py
lauexplore/_utils/_hide_print.py
lauexplore/_utils/chunks.py
lauexplore/_utils/strings.py
lauexplore/constants/motors.py
lauexplore/dataset/__init__.py
lauexplore/dataset/_dataset.py
lauexplore/dataset/_indexation_quality.py
lauexplore/dataset/_strain.py
lauexplore/emission/__init__.py
lauexplore/emission/_fluorescence.py
lauexplore/emission/_xeol.py
lauexplore/image/__init__.py
lauexplore/image/_mosaic.py
lauexplore/image/_plot.py
lauexplore/image/_read.py
lauexplore/image/_roi.py
lauexplore/image/image.py
lauexplore/peaks/__init__.py
lauexplore/peaks/_duplicates.py
lauexplore/peaks/_indexation.py
lauexplore/peaks/_intersect.py
lauexplore/peaks/_simulate.py
lauexplore/peaks/_subtract.py
lauexplore/peaks/_track.py
lauexplore/plots/__init__.py
lauexplore/plots/base.py
lauexplore/plots/composite.py
lauexplore/plots/hovermenus.py
lauexplore/scan/__init__.py
lauexplore/scan/_scan.py
lauexplore/scan/crop.py
lauexplore-1.0.3.dist-info/licenses/LICENSE
lauexplore-1.0.3.dist-info/METADATA
lauexplore-1.0.3.dist-info/WHEEL
lauexplore-1.0.3.dist-info/top_level.txt
lauexplore-1.0.3.dist-info/RECORD
