Metadata-Version: 2.4
Name: lauexplore
Version: 1.0.3
Summary: Post processing tools for data produced by the lauetools package.
Author-email: Sergio Bongiorno <sergiobng@proton.me>, Beatriz G Foschiani <beatrizgfoschiani@gmail.com>
Maintainer-email: Beatriz G Foschiani <beatrizgfoschiani@gmail.com>
License: MIT
Requires-Python: >=3.8
License-File: LICENSE
Requires-Dist: numpy
Requires-Dist: scipy
Requires-Dist: matplotlib==3.9.*
Requires-Dist: pandas
Requires-Dist: h5py
Requires-Dist: fabio
Requires-Dist: scikit-image
Requires-Dist: scikit-learn
Requires-Dist: plotly==6.*
Requires-Dist: kaleido
Requires-Dist: anywidget>=0.9
Requires-Dist: ipykernel
Requires-Dist: jupyterlab
Requires-Dist: ipympl
Requires-Dist: ipywidgets
Requires-Dist: widgetsnbextension
Requires-Dist: lauetools==3.1.19
Provides-Extra: dev
Requires-Dist: pytest; extra == "dev"
Requires-Dist: black; extra == "dev"
Requires-Dist: flake8; extra == "dev"
Dynamic: license-file
